{"data": {"__GLOBAL": {"_ATTACH_BASE_VIEW": "img.nga.178.com/attachments"}, "__U": {"150058": {"uid": 150058, "username": "UID:150058", "credit": 135537154, "medal": "272,207,157,92", "reputation": "28_30,61_0,147_775,130_10", "groupid": -1, "memberid": 73, "avatar": null, "yz": 4, "site": null, "honor": null, "regdate": 1123989606, "mute_time": null, "postnum": 41079, "rvrc": 29, "money": 90765, "thisvisit": 1782044211, "signature": null, "nickname": null, "bit_data": 135537154}, "66989363": {"uid": 66989363, "username": "UID:66989363", "credit": 135275008, "medal": null, "reputation": "147_-300", "groupid": -1, "memberid": 39, "avatar": null, "yz": 4, "site": null, "honor": null, "regdate": 1762774156, "mute_time": null, "postnum": 2701, "rvrc": 10, "money": 0, "thisvisit": 1782082361, "signature": null, "nickname": null, "bit_data": 135275008}, "__GROUPS": {"73": ["学徒", 360672, 73], "39": ["学徒", 98528, 39]}, "__MEDALS": {"272": ["272.gif", "棒棒糖", "叔叔请你吃棒棒糖", 272], "207": ["207.gif", "爆竹声中旧岁除", "一支红杏出墙来", 207], "157": ["157.gif", "王者之剑", "王者之剑活动纪念", 157], "92": ["92.gif", "小心死亡之翼-", "2011年大灾变开服纪念", 92]}, "__REPUTATIONS": {"147": {"150058": 775, "66989363": -300, "0": "大时代"}}}, "__R": [{"pid": 859265580, "fid": 706, "tid": 45974302, "authorid": 150058, "type": 0, "score": 31, "score_2": 0, "recommend": 0, "postdate": "2026-02-26 13:31", "subject": "", "alterinfo": "", "content": "你们知道为什么现在横在这里么  谁在压 目的是等谁上 如果拉红是什么技术形态  你们都了解么", "lou": 920, "content_length": 80, "from_client": "0 /", "postdatetimestamp": 1772083892}, {"pid": 859266192, "fid": 706, "tid": 45974302, "authorid": 150058, "type": 0, "score": 39, "score_2": 0, "recommend": 0, "postdate": "2026-02-26 13:37", "subject": "", "alterinfo": "", "content": "。。看来你们完全不理解现在是什么情况啊。。。算了  你们慢慢来吧  现在理解不了盘口语言", "lou": 921, "content_length": 80, "from_client": "0 /", "postdatetimestamp": 1772084238}, {"pid": 859266768, "fid": 706, "tid": 45974302, "authorid": 150058, "type": 0, "score": 14, "score_2": 0, "recommend": 0, "postdate": "2026-02-26 13:42", "subject": "", "alterinfo": "", "content": "[quote][pid=859266625,45974302,1675]Reply[/pid] [b]Post by [uid=37784933]e471167749[/uid] (2026-02-26 13:41):[/b]<br/><br/>寒武纪科技表态了，那应该是在等券商表态。。[s:ac:哭笑][/quote]<br/>寒武纪是因为消息说H200又暂时进不来了  。。。。。", "lou": 922, "content_length": 51, "reply_to": 859266625, "from_client": "0 /", "postdatetimestamp": 1772084565}, {"pid": 859267793, "fid": 706, "tid": 45974302, "authorid": 150058, "type": 0, "score": 57, "score_2": 0, "recommend": 0, "postdate": "2026-02-26 13:52", "subject": "", "alterinfo": "", "content": "等什么。。等机构分仓去金融顶过今天开盘价收盘啊<br/>这里不管拉多少科技都没用，机构必须要去买金融，否则就是上不去。但是机构也不是傻的 没人愿意大公无私去，或者没钱去了<br/>就像我一样 我就没钱去金融了。想买都没办法。", "lou": 923, "content_length": 200, "from_client": "0 /", "postdatetimestamp": 1772085145}, {"pid": 859268053, "fid": 706, "tid": 45974302, "authorid": 150058, "type": 0, "score": 17, "score_2": 0, "recommend": 0, "postdate": "2026-02-26 13:54", "subject": "", "alterinfo": "", "content": "[quote][pid=859267251,45974302,1676]Reply[/pid] [b]Post by [uid=66522287]金灿灿*[/uid] (2026-02-26 13:47):[/b]<br/><br/>狼大说的晟腾链，昨天观测到意华股份，买了点，走的很漂亮[/quote]<br/>我今天卖了  提示你一下 他是华丰小弟", "lou": 924, "content_length": 37, "reply_to": 859267251, "from_client": "0 /", "postdatetimestamp": 1772085287}, {"pid": 859268444, "fid": 706, "tid": 45974302, "authorid": 150058, "type": 0, "score": 8, "score_2": 0, "recommend": 0, "postdate": "2026-02-26 13:58", "subject": "", "alterinfo": "", "content": "[quote][pid=859268140,45974302,1677]Reply[/pid] [b]Post by [uid=65664557]维拉帕米不是米[/uid] (2026-02-26 13:55):[/b]<br/><br/>机构除了科技之外的仓位是不是要减完然后拉券商啊，那得先看看白酒大跌后再考虑券商的拉升问题啊[/quote]<br/>机构都有活动仓位的 这些仓位可以灵活操作短期", "lou": 925, "content_length": 47, "reply_to": 859268140, "from_client": "0 /", "postdatetimestamp": 1772085500}, {"pid": 859268960, "fid": 706, "tid": 45974302, "authorid": 150058, "type": 0, "score": 20, "score_2": 0, "recommend": 0, "postdate": "2026-02-26 14:02", "subject": "", "alterinfo": "", "content": "[quote][pid=859268687,45974302,1678]Reply[/pid] [b]Post by [uid=62368609]xiaohuo1992[/uid] (2026-02-26 14:00):[/b]<br/><br/>看到往下砸，第一时间看了银保地石油中字头大屁股，幅度不大甚至没动静，那么确认不像是gjd砸的，科技类反而有一段很明显同步下砸的，那么结合国家队最近差不多了，应该是鼓励市场自发突破，等待机构去金融带市场起来，目前又开始缩量，证明观望情绪又起来了，等一只穿云箭。<br/><br/>btw,如果这时候拉起，那就是突破三角收敛回踩确认的起爆点？<br/><br/>不知道我这个观测对不对[s:ac:哭笑][/quote]<br/>如果收红就是揉搓线啊 日K双底回中轨确认后的红色揉搓线。上一次我说这个话是哪个票来着？", "lou": 926, "content_length": 88, "reply_to": 859268687, "from_client": "0 /", "postdatetimestamp": 1772085776}, {"pid": 859269311, "fid": 706, "tid": 45974302, "authorid": 150058, "type": 0, "score": 24, "score_2": 0, "recommend": 0, "postdate": "2026-02-26 14:06", "subject": "", "alterinfo": "", "content": "[quote][pid=859269190,45974302,1678]Reply[/pid] [b]Post by [uid=38806682]墨迹格[/uid] (2026-02-26 14:05):[/b]<br/><br/>这里一片欢声笑语，切出去一看，3000+下跌了，我们真的是大盘反指啊[/quote]<br/>放屁 昨天前天没涨？", "lou": 927, "content_length": 23, "reply_to": 859269190, "from_client": "0 /", "postdatetimestamp": 1772085966}, {"pid": 859269461, "fid": 706, "tid": 45974302, "authorid": 150058, "type": 0, "score": 29, "score_2": 0, "recommend": 0, "postdate": "2026-02-26 14:07", "subject": "", "alterinfo": "", "content": "[quote][pid=859269093,45974302,1678]Reply[/pid] [b]Post by [uid=42093899]加薪的饼干[/uid] (2026-02-26 14:04):[/b]<br/><br/>简单看了下大盘，现在缺乏两个方面的信号，<br/><br/>一个是量能还不足以支撑突破，午盘之后大盘量缩得厉害，别看深指和科技拉出火，大盘整体却还是大缩量，不放量就不能突破以及上冲关键点位需要15分钟K线持续稳定放量，这是狼大说过的。<br/><br/>二个是非银金融还没有任何动作，今年的基调就是科技+金融才是真突破，无论是前天非银动科技不动还是今天科技动金融不动，都只是炒热大盘气氛不至于冷场，少一边都不能实现突破，也是狼大说过的。<br/><br/>然后说点题外话，有的老哥说横盘掩护机构调仓我觉得不对，机构和柚子散户风格不一样很多时候看着火[/quote]<br/>好歹像这个一样用点脑。。。。", "lou": 928, "content_length": 33, "reply_to": 859269093, "from_client": "0 /", "postdatetimestamp": 1772086042}, {"pid": 859269726, "fid": 706, "tid": 45974302, "authorid": 150058, "type": 0, "score": 21, "score_2": 0, "recommend": 0, "postdate": "2026-02-26 14:09", "subject": "", "alterinfo": "", "content": "[quote][pid=859269328,45974302,1679]Reply[/pid] [b]Post by [uid=38140916]huohuo277[/uid] (2026-02-26 14:06):[/b]<br/><br/>大盘也能套这个指标的吗[s:ac:哭笑]果然是最大的庄股[/quote]<br/>很多人之前都说 大盘不可能控制 没人能控制 说能控制的都是臆想，最近一年这种话很少了", "lou": 929, "content_length": 83, "reply_to": 859269328, "from_client": "0 /", "postdatetimestamp": 1772086183}, {"pid": 859272302, "fid": 706, "tid": 45974302, "authorid": 150058, "type": 0, "score": 27, "score_2": 0, "recommend": 0, "postdate": "2026-02-26 14:31", "subject": "", "alterinfo": "", "content": "[quote][pid=859272158,45974302,1681]Reply[/pid] [b]Post by [uid=60027718]xiaomiwang1[/uid] (2026-02-26 14:30):[/b]<br/><br/>外面已经看到有人看空大盘腰斩了[/quote]<br/>这么屌吗？什么逻辑？", "lou": 930, "content_length": 25, "reply_to": 859272158, "from_client": "0 /", "postdatetimestamp": 1772087501}, {"pid": 859273389, "fid": 706, "tid": 45974302, "authorid": 150058, "type": 0, "score": 54, "score_2": 0, "recommend": 0, "postdate": "2026-02-26 14:39", "subject": "", "alterinfo": "", "content": "幸好年前转回来一大笔钱 不然这个汇率都让我亏不少 啧啧<br/>又做了个正确的事情", "lou": 931, "content_length": 68, "from_client": "0 /", "postdatetimestamp": 1772087998}, {"pid": 859276209, "fid": 706, "tid": 45974302, "authorid": 150058, "type": 0, "score": 49, "score_2": 0, "recommend": 0, "postdate": "2026-02-26 15:00", "subject": "", "alterinfo": "", "content": "可惜了  没拉金融 所以没出顶级走势  慢慢来吧 没有顶级狂暴走势了。", "lou": 932, "content_length": 58, "from_client": "0 /", "postdatetimestamp": 1772089251}, {"pid": 859277194, "fid": 706, "tid": 45974302, "authorid": 150058, "type": 0, "score": 61, "score_2": 0, "recommend": 0, "postdate": "2026-02-26 15:08", "subject": "", "alterinfo": "", "content": "算了 能收3天红包就不错了  应该没有人这三天不挣钱吧", "lou": 933, "content_length": 47, "from_client": "0 /", "postdatetimestamp": 1772089703}, {"pid": 859277870, "fid": 706, "tid": 45974302, "authorid": 150058, "type": 0, "score": 33, "score_2": 0, "recommend": 0, "postdate": "2026-02-26 15:13", "subject": "", "alterinfo": "", "content": "[quote][pid=859277556,45974302,1687]Reply[/pid] [b]Post by [uid=64289495]生鱼片是死鱼片wk[/uid] (2026-02-26 15:11):[/b]<br/><br/>懂了，明天开始扣钱[s:ac:吓][/quote]<br/>没有吧 我明天不减", "lou": 934, "content_length": 21, "reply_to": 859277556, "from_client": "0 /", "postdatetimestamp": 1772089998}, {"pid": 859278560, "fid": 706, "tid": 45974302, "authorid": 150058, "type": 0, "score": 37, "score_2": 0, "recommend": 0, "postdate": "2026-02-26 15:18", "subject": "", "alterinfo": "", "content": "[quote][pid=859278184,45974302,1687]Reply[/pid] [b]Post by [uid=41746951]ouohoo[/uid] (2026-02-26 15:15):[/b]<br/><br/>今天是周四哦 别忘了逆回购[s:ac:怕][/quote]<br/>他们哪还有钱逆回购 不杠杆就不错了", "lou": 935, "content_length": 37, "reply_to": 859278184, "from_client": "0 /", "postdatetimestamp": 1772090288}, {"pid": 859289859, "fid": 706, "tid": 45974302, "authorid": 150058, "type": 0, "score": 61, "score_2": 0, "recommend": 0, "postdate": "2026-02-26 16:39", "subject": "", "alterinfo": "", "content": "[quote][pid=859289147,45974302,1693]Reply[/pid] [b]Post by [uid=1003090]zzh90pk[/uid] (2026-02-26 16:34):[/b]<br/><br/>这个有用，但是也不用太惊讶。前段时间我这种菜鸡都能推出mt一个买点是112左右，简单粗暴的最高点140减20%。我也真买了，虽然仓位不大。我是在企稳后115左右买的。<br/>真正难的是，为什么对mt用这招？真这么简单的策略量化不早就随便捡钱了？因为你信它后续能涨。很多板块你用试试，一用一个不吱声[s:ac:哭笑]<br/>这个的背后是整套的选股逻辑，这个是真的难，但是狼大给到细分方向已经直接帮我们把最难关过了。[/quote]<br/>之前说过了  技术指标是找资金共性 你能在刚好的技术指标买进卖出证明里面的资金也是用这套，大家合得来就一起收割看不懂的。如果这个票不合你的技术指标 就证明你和里面的资金用的不是同一套，那就拼钱和耐心<br/>我筛出来的票你们看到和我用的技术策略一样就是这么个事了  其实大盘5000多只 不同的更多。", "lou": 936, "content_length": 277, "reply_to": 859289147, "from_client": "0 /", "postdatetimestamp": 1772095157}, {"pid": 859290562, "fid": 706, "tid": 45974302, "authorid": 150058, "type": 0, "score": 103, "score_2": 0, "recommend": 0, "postdate": "2026-02-26 16:44", "subject": "", "alterinfo": "", "content": "其实你们晒收益不会影响大盘，只是晒的人多了 证明市场过热，那就防止短时间分歧就行了 不用把自己想象得过重 大家在地球online里面只是个NPC<br/>还有 我AI硬目前就4只主力票，其他那种小的票放不了太多钱的，不占什么仓位，目前这部分仓位20%<br/>因为我钱确实不少了 希望这两年趁行情好能过10 那应该就能收手了", "lou": 937, "content_length": 275, "from_client": "0 /", "postdatetimestamp": 1772095454}, {"pid": 859291277, "fid": 706, "tid": 45974302, "authorid": 150058, "type": 0, "score": 53, "score_2": 0, "recommend": 0, "postdate": "2026-02-26 16:49", "subject": "", "alterinfo": "", "content": "[quote][pid=859290720,45974302,1694]Reply[/pid] [b]Post by [uid=61649350]FutureMax002[/uid] (2026-02-26 16:45):[/b]<br/><br/>狼大，你教我们是希望我们用跟你一样的逻辑形成合力吗？[s:a2:不明觉厉]<br/>但我感觉不差我这点啊[s:ac:怕][/quote]<br/>确实不差你们这点  但是楼内可能有隐形大户 我不希望我的趋势票被这种几百个几百个的乱搞。趋势一旦形成 就需要维护，一旦中间某些支撑位被这些不坚定的资金弄破，修复起来要花很大的时间和金钱", "lou": 938, "content_length": 181, "reply_to": 859290720, "from_client": "0 /", "postdatetimestamp": 1772095752}, {"pid": 859292210, "fid": 706, "tid": 45974302, "authorid": 150058, "type": 0, "score": 65, "score_2": 0, "recommend": 0, "postdate": "2026-02-26 16:55", "subject": "", "alterinfo": "", "content": "[quote][pid=859291496,45974302,1694]Reply[/pid] [b]Post by [uid=62862742]織田信姬[/uid] (2026-02-26 16:50):[/b]<br/><br/>确实学了不少东西啊 谢谢狼大[s:ac:茶][/quote]<br/>万一我哪天着草的时候记得给我发点路费就行了 留个后手", "lou": 939, "content_length": 55, "reply_to": 859291496, "from_client": "0 /", "postdatetimestamp": 1772096136}], "__T": {"fid": 706, "tid": 45974302, "topic_misc": null, "subject": "自立自强，科学技术打头阵", "locked": 0, "recommend": 0, "quote_to": null, "quote_from": 0, "type": 36, "replies": 155486, "authorid": 150058, "postdate": 1768179906, "lastpost": 1782109223, "jdata": null, "author": "-阿狼-", "lastposter": "江东jump", "digest": 0, "lastmodify": 1782109245, "tpid": 0, "post_misc_var": {"content_length": 412, "fid": 706, "comment_id": ",854270755,860174433", "14": {"17": 1, "14": 4, "13": 4, "12": 1}, "16": "63335896,19412700,26652007,67067074,20672033,66881586,67068843,66199622,60819388,60409766,67057614,60264977,61082281,42701832,66998841,61574956,61272875,67082978,66949654,65530601,60630412,60240136,66038632,63481990,61973100,60192597,66985104,19043499,39108806,41714633,7046671,65647302,40696141,3481707,654677,39235785,66063392,39314790,67071606,66251279,42126891,61602239,4785041,42995612,67024871,62241578,64199867,11586486,5641907,66685489,66633842,65208818,42941765,,42964685,42181525,14317962,67086252,34699482,62593385,67000864,64005788,62799978,60424140,42468630,61560061,67096060,61021164,67102441,63220970,19312329,60694817,67086969,67061200,60701305,66937546,62357329,41746951,60027718,,39248719,62403348,40776497,67088120,66875016,64268963,1459804,67062343,12177085,38702942,1383368,67093370,66885146,40024017,63922791,67095295,66895557,64571355,62824316,5495109,38806682,67122547,67137453,67078475,,38110681,66618696,64658121,67085304,38883076,67132556,67126715,62653482,67128658,64731349,67105996,65464857,67143142,67118412,36620789,62234787,67115759,67136133,2062702,4627122,67095345,67145169,67105952,67054948,67085379,66758380,43207490,37784933,19483255,34874814,37791497,14884234,64997287,63841614,8555597,67098132,62368609,39205700,42258905,61649350,1224802,41288139,67150573,60252995,66801275,2251556,66907545,67004473,67088624,67103794,42700304,67193496,40810297,67210279,,64942487,1134755,60347315,67236214,66144535,63849256", "17": ",867926538,854270809,869804045,857316962"}, "this_visit_rows": 3375}, "__F": {"custom_level": "[{r:-21000,n:\"内鬼\"},{r:-500,n:\"st退\"},{r:-1,n:\"A股新秀\"},{r:150,n:\"每日打新\"},{r:300,n:\"扒车高手\"},{r:500,n:\"做t能手\"},{r:1000,n:\"两融侠客\"},{r:2000,n:\"技术达人\"},{r:3500,n:\"大时代证监会\"},{r:5000,n:\"基金经理\"},{r:10000,n:\"投行专家\"},{r:15000,n:\"股市大亨\"},{r:20000,n:\"万神殿\"}]", "name": "大时代"}, "__R__ROWS": 20, "__R__ROWS_PAGE": 20, "__ROWS": 3375, "__PAGE": 47}, "time": 1782109245}