{"data": {"__GLOBAL": {"_ATTACH_BASE_VIEW": "img.nga.178.com/attachments"}, "__U": {"150058": {"uid": 150058, "username": "UID:150058", "credit": 135537154, "medal": "272,207,157,92", "reputation": "28_30,61_0,147_775,130_10", "groupid": -1, "memberid": 73, "avatar": null, "yz": 4, "site": null, "honor": null, "regdate": 1123989606, "mute_time": null, "postnum": 41079, "rvrc": 29, "money": 90765, "thisvisit": 1782044211, "signature": null, "nickname": null, "bit_data": 135537154}, "66989363": {"uid": 66989363, "username": "UID:66989363", "credit": 135275008, "medal": null, "reputation": "147_-300", "groupid": -1, "memberid": 39, "avatar": null, "yz": 4, "site": null, "honor": null, "regdate": 1762774156, "mute_time": null, "postnum": 2701, "rvrc": 10, "money": 0, "thisvisit": 1782082361, "signature": null, "nickname": null, "bit_data": 135275008}, "__GROUPS": {"73": ["学徒", 360672, 73], "39": ["学徒", 98528, 39]}, "__MEDALS": {"272": ["272.gif", "棒棒糖", "叔叔请你吃棒棒糖", 272], "207": ["207.gif", "爆竹声中旧岁除", "一支红杏出墙来", 207], "157": ["157.gif", "王者之剑", "王者之剑活动纪念", 157], "92": ["92.gif", "小心死亡之翼-", "2011年大灾变开服纪念", 92]}, "__REPUTATIONS": {"147": {"150058": 775, "66989363": -300, "0": "大时代"}}}, "__R": [{"pid": 854769757, "fid": 706, "tid": 45974302, "authorid": 150058, "type": 0, "score": 21, "score_2": 0, "recommend": 0, "postdate": "2026-01-16 10:46", "subject": "", "alterinfo": "", "content": "[quote][pid=854769483,45974302,285]Reply[/pid] [b]Post by [uid=60436766]稲橋[/uid] (2026-01-16 10:44):[/b]<br/><br/>狼大，请问今天华翔能指点一二么？ 新主力筹码收够了结合板块行情拉升？[s:ac:喘][/quote]<br/>低位补涨吧  落后我4大机器人至少50%以上", "lou": 160, "content_length": 41, "reply_to": 854769483, "from_client": "0 /", "postdatetimestamp": 1768531609}, {"pid": 854769974, "fid": 706, "tid": 45974302, "authorid": 150058, "type": 8192, "score": 37, "score_2": 0, "recommend": 0, "postdate": "2026-01-16 10:48", "subject": "", "alterinfo": "", "content": "[img]./mon_202601/16/jmQktl-40adK13T3cSvo-69.jpg[/img]<br/>赶紧卖铜", "lou": 161, "content_length": 47, "attachs": [{"attachurl": "mon_202601/16/jmQktl-40adK13T3cSvo-69.jpg", "size": 39, "type": "img", "subid": 0, "url_utf8_org_name": "image%2epng", "dscp": "", "path": "mon_202601/16", "name": "jmQktl-40adK13T3cSvo-69.jpg", "ext": "jpg", "thumb": "120"}], "from_client": "0 /", "postdatetimestamp": 1768531691}, {"pid": 854771045, "fid": 706, "tid": 45974302, "authorid": 150058, "type": 0, "score": 8, "score_2": 0, "recommend": 0, "postdate": "2026-01-16 10:55", "subject": "", "alterinfo": "", "content": "[quote][pid=854770743,45974302,288]Reply[/pid] [b]Post by [uid=37838420]zsc00123456789[/uid] (2026-01-16 10:53):[/b]<br/><br/>那是不是可以开始建仓了[s:ac:惊][/quote]<br/>我不去 我做四个就做不过来了", "lou": 162, "content_length": 31, "reply_to": 854770743, "from_client": "0 /", "postdatetimestamp": 1768532120}, {"pid": 854771827, "fid": 706, "tid": 45974302, "authorid": 150058, "type": 0, "score": 12, "score_2": 0, "recommend": 0, "postdate": "2026-01-16 11:00", "subject": "", "alterinfo": "", "content": "[quote][pid=854771615,45974302,289]Reply[/pid] [b]Post by [uid=66643290]redasjs[/uid] (2026-01-16 10:59):[/b]<br/><br/>这会改变2026整年大宗涨价的逻辑吗，还是影响短期情绪[/quote]<br/>短期", "lou": 163, "content_length": 9, "reply_to": 854771615, "from_client": "0 /", "postdatetimestamp": 1768532449}, {"pid": 854773072, "fid": 706, "tid": 45974302, "authorid": 150058, "type": 0, "score": 14, "score_2": 0, "recommend": 0, "postdate": "2026-01-16 11:08", "subject": "", "alterinfo": "", "content": "[quote][pid=854772431,45974302,289]Reply[/pid] [b]Post by [uid=62771233]极地丶之光[/uid] (2026-01-16 11:04):[/b]<br/><br/>我认为是短期影响，铜涨价的因素不光是数据中心建设，包括铜矿品位下降，勘探困难，冶炼倒挂等，铜的周期应该很长，至少是以年为单位的[/quote]<br/>主要是大放水时代", "lou": 164, "content_length": 21, "reply_to": 854772431, "from_client": "0 /", "postdatetimestamp": 1768532930}, {"pid": 854788466, "fid": 706, "tid": 45974302, "authorid": 150058, "type": 0, "score": 20, "score_2": 0, "recommend": 0, "postdate": "2026-01-16 13:09", "subject": "", "alterinfo": "", "content": "[quote][pid=854788395,45974302,297]Reply[/pid] [b]Post by [uid=67011972]Maxyuuka[/uid] (2026-01-16 13:09):[/b]<br/><br/>卫星只要涨gjd就砸盘吗[/quote]<br/>国家队不会去砸卫星的 因为没有筹码", "lou": 165, "content_length": 37, "reply_to": 854788395, "from_client": "0 /", "postdatetimestamp": 1768540187}, {"pid": 854789268, "fid": 706, "tid": 45974302, "authorid": 150058, "type": 0, "score": 8, "score_2": 0, "recommend": 0, "postdate": "2026-01-16 13:17", "subject": "", "alterinfo": "", "content": "[quote][pid=854788904,45974302,298]Reply[/pid] [b]Post by [uid=63397510]ゆっちゃ[/uid] (2026-01-16 13:13):[/b]<br/><br/>狼大，这个消息昨天就在发酵，铜今天还高走，是不是代表本身逻辑不怕这个消息[/quote]<br/>晚上看夜盘期铜就懂了 崩就是借利空套利", "lou": 166, "content_length": 41, "reply_to": 854788904, "from_client": "0 /", "postdatetimestamp": 1768540648}, {"pid": 854789404, "fid": 706, "tid": 45974302, "authorid": 150058, "type": 0, "score": 69, "score_2": 0, "recommend": 0, "postdate": "2026-01-16 13:18", "subject": "", "alterinfo": "", "content": "[quote][pid=854788984,45974302,298]Reply[/pid] [b]Post by [uid=64973700]SpamSender[/uid] (2026-01-16 13:14):[/b]<br/><br/>170和516是不是可以做一些高低切，看谁涨幅落后的就跳过去吃点补涨[/quote]<br/>你这么牛X吗。。。我从来没想过这种打法 ETF横跳套利？", "lou": 167, "content_length": 55, "reply_to": 854788984, "from_client": "0 /", "postdatetimestamp": 1768540725}, {"pid": 854789809, "fid": 706, "tid": 45974302, "authorid": 150058, "type": 0, "score": 7, "score_2": 0, "recommend": 0, "postdate": "2026-01-16 13:22", "subject": "", "alterinfo": "", "content": "[quote][pid=854789624,45974302,299]Reply[/pid] [b]Post by [uid=65306601]ccckkk1[/uid] (2026-01-16 13:20):[/b]<br/><br/>巨力是不是也符合双跌停[s:a2:不明觉厉][/quote]<br/>对  开板就符合 不过最好上午开板  证明资金比较急切", "lou": 168, "content_length": 49, "reply_to": 854789624, "from_client": "0 /", "postdatetimestamp": 1768540964}, {"pid": 854790365, "fid": 706, "tid": 45974302, "authorid": 150058, "type": 0, "score": 26, "score_2": 0, "recommend": 0, "postdate": "2026-01-16 13:28", "subject": "", "alterinfo": "", "content": "[quote][pid=854790210,45974302,300]Reply[/pid] [b]Post by [uid=65329649]zippo578[/uid] (2026-01-16 13:26):[/b]<br/><br/>国家队画图真牛皮[s:ac:哭笑][/quote]<br/>不懂技术的是不是完全看不懂  能看懂的才能互相沟通  就和那些学霸解微积分觉得很爽一样   我也完全不能理解", "lou": 169, "content_length": 99, "reply_to": 854790210, "from_client": "0 /", "postdatetimestamp": 1768541283}, {"pid": 854790729, "fid": 706, "tid": 45974302, "authorid": 150058, "type": 0, "score": 24, "score_2": 0, "recommend": 0, "postdate": "2026-01-16 13:31", "subject": "", "alterinfo": "", "content": "你们注意一下光刻机", "lou": 170, "content_length": 18, "from_client": "0 /", "postdatetimestamp": 1768541483}, {"pid": 854791358, "fid": 706, "tid": 45974302, "authorid": 150058, "type": 0, "score": 38, "score_2": 0, "recommend": 0, "postdate": "2026-01-16 13:37", "subject": "", "alterinfo": "", "content": "量化硬切半导体了  从航天和AI应用过来了 柚子和散户估计还要等一下", "lou": 171, "content_length": 60, "from_client": "0 /", "postdatetimestamp": 1768541853}, {"pid": 854792184, "fid": 706, "tid": 45974302, "authorid": 150058, "type": 0, "score": 75, "score_2": 0, "recommend": 0, "postdate": "2026-01-16 13:44", "subject": "", "alterinfo": "", "content": "注意了  每一次半导体行情短期最后都是光刻机和EDA IGBT那些收尾<br/>目前开始有点点迹象。但是还没爆发 这个给你们自己拿来当参考 不用一天担惊受怕4个小时要不要跑", "lou": 172, "content_length": 144, "from_client": "0 /", "postdatetimestamp": 1768542273}, {"pid": 854792544, "fid": 706, "tid": 45974302, "authorid": 150058, "type": 0, "score": 30, "score_2": 0, "recommend": 0, "postdate": "2026-01-16 13:47", "subject": "", "alterinfo": "", "content": "[b]Reply to [pid=854792444,45974302,303]Reply[/pid] Post by [uid=63220970]攻城狮17号[/uid] (2026-01-16 13:46)[/b]<br/>哈哈哈哈哈哈！！！！！！！！！！！！！！！！！！！！！", "lou": 173, "content_length": 87, "reply_to": 854792444, "from_client": "0 /", "postdatetimestamp": 1768542460}, {"pid": 854793021, "fid": 706, "tid": 45974302, "authorid": 150058, "type": 0, "score": 21, "score_2": 0, "recommend": 0, "postdate": "2026-01-16 13:51", "subject": "", "alterinfo": "", "content": "[quote][pid=854792686,45974302,304]Reply[/pid] [b]Post by [uid=65329649]zippo578[/uid] (2026-01-16 13:48):[/b]<br/><br/>忍一忍，很快就不疼了.jpg?????[/quote]<br/>注意 机构会压盘的，没到时间 也不愿意这个时候  毕竟上面还在管控期间，机构不是SB", "lou": 174, "content_length": 79, "reply_to": 854792686, "from_client": "0 /", "postdatetimestamp": 1768542698}, {"pid": 854794118, "fid": 706, "tid": 45974302, "authorid": 150058, "type": 0, "score": 16, "score_2": 0, "recommend": 0, "postdate": "2026-01-16 14:01", "subject": "", "alterinfo": "", "content": "[quote][pid=854793867,45974302,305]Reply[/pid] [b]Post by [uid=60099555]咪了个咕[/uid] (2026-01-16 13:58):[/b]<br/><br/>狼大，今天按纪律还是6成仓吗？[/quote]<br/>对 除非重回上涨趋势或者给我抓到那个底", "lou": 175, "content_length": 41, "reply_to": 854793867, "from_client": "0 /", "postdatetimestamp": 1768543263}, {"pid": 854794728, "fid": 706, "tid": 45974302, "authorid": 150058, "type": 0, "score": 21, "score_2": 0, "recommend": 0, "postdate": "2026-01-16 14:06", "subject": "", "alterinfo": "", "content": "[quote][pid=854794044,45974302,306]Reply[/pid] [b]Post by [uid=65329649]zippo578[/uid] (2026-01-16 14:00):[/b]<br/><br/>还要磨啊[s:pg:哭][/quote]<br/>你看刚才半导体想突破的那一下银行在干嘛  盘口语言啊。。", "lou": 176, "content_length": 57, "reply_to": 854794044, "from_client": "0 /", "postdatetimestamp": 1768543575}, {"pid": 854795255, "fid": 706, "tid": 45974302, "authorid": 150058, "type": 0, "score": 104, "score_2": 0, "recommend": 0, "postdate": "2026-01-16 14:10", "subject": "", "alterinfo": "", "content": "[quote][pid=854794813,45974302,306]Reply[/pid] [b]Post by [uid=607563]marklzm[/uid] (2026-01-16 14:07):[/b]<br/><br/>我感觉你们是不是都领会错了狼大的意思[s:ac:哭笑]他说关注光刻机eda不是让你们买，意思是你们观察他们作为行情尾端的指标，这样不用每天担惊受怕想跑路，什么时候这些冲了什么时候跑路就行了，不是让你们现在买，我感觉狼大是这个意思[s:ac:哭笑][/quote]<br/>牛P 中译中  完全没想到在论坛还能看到做阅读理解的。。。。。。<br/>姑且给你满分吧", "lou": 177, "content_length": 76, "reply_to": 854794813, "from_client": "0 /", "postdatetimestamp": 1768543832}, {"pid": 854795514, "fid": 706, "tid": 45974302, "authorid": 150058, "type": 0, "score": 19, "score_2": 0, "recommend": 0, "postdate": "2026-01-16 14:12", "subject": "", "alterinfo": "", "content": "[quote][pid=854795137,45974302,307]Reply[/pid] [b]Post by [uid=9032340]letuswowing[/uid] (2026-01-16 14:09):[/b]<br/><br/>狼大 能讲下拖进为什么不让涨的原因么[/quote]<br/>拓经有1/3属性是板块指数核心 ，位置等同于CPO里易中天里面的新医生", "lou": 178, "content_length": 67, "reply_to": 854795137, "from_client": "0 /", "postdatetimestamp": 1768543965}, {"pid": 854796221, "fid": 706, "tid": 45974302, "authorid": 150058, "type": 0, "score": 32, "score_2": 0, "recommend": 0, "postdate": "2026-01-16 14:18", "subject": "", "alterinfo": "", "content": "[quote][pid=854795706,45974302,308]Reply[/pid] [b]Post by [uid=607563]marklzm[/uid] (2026-01-16 14:14):[/b]<br/><br/>谢谢狼大肯定[s:ac:哭笑]不过我感觉冲了的兄弟也没啥关系，亏不了啥钱，当埋伏也没问题感觉[/quote]<br/>亏倒是不会亏 但是他们不会做光刻机<br/>光刻机行情是盘久 然后突然一下爆发的 大部分人忍不到那个阶段  或者在爆发的第一秒就卖掉<br/>光刻机不适合大部分人做", "lou": 179, "content_length": 139, "reply_to": 854795706, "from_client": "0 /", "postdatetimestamp": 1768544308}], "__T": {"fid": 706, "tid": 45974302, "topic_misc": null, "subject": "自立自强，科学技术打头阵", "locked": 0, "recommend": 0, "quote_to": null, "quote_from": 0, "type": 36, "replies": 155484, "authorid": 150058, "postdate": 1768179906, "lastpost": 1782109184, "jdata": null, "author": "-阿狼-", "lastposter": "zippo578", "digest": 0, "lastmodify": 1782109187, "tpid": 0, "post_misc_var": {"content_length": 412, "fid": 706, "comment_id": ",854270755,860174433", "14": {"17": 1, "14": 4, "13": 4, "12": 1}, "16": "63335896,19412700,26652007,67067074,20672033,66881586,67068843,66199622,60819388,60409766,67057614,60264977,61082281,42701832,66998841,61574956,61272875,67082978,66949654,65530601,60630412,60240136,66038632,63481990,61973100,60192597,66985104,19043499,39108806,41714633,7046671,65647302,40696141,3481707,654677,39235785,66063392,39314790,67071606,66251279,42126891,61602239,4785041,42995612,67024871,62241578,64199867,11586486,5641907,66685489,66633842,65208818,42941765,,42964685,42181525,14317962,67086252,34699482,62593385,67000864,64005788,62799978,60424140,42468630,61560061,67096060,61021164,67102441,63220970,19312329,60694817,67086969,67061200,60701305,66937546,62357329,41746951,60027718,,39248719,62403348,40776497,67088120,66875016,64268963,1459804,67062343,12177085,38702942,1383368,67093370,66885146,40024017,63922791,67095295,66895557,64571355,62824316,5495109,38806682,67122547,67137453,67078475,,38110681,66618696,64658121,67085304,38883076,67132556,67126715,62653482,67128658,64731349,67105996,65464857,67143142,67118412,36620789,62234787,67115759,67136133,2062702,4627122,67095345,67145169,67105952,67054948,67085379,66758380,43207490,37784933,19483255,34874814,37791497,14884234,64997287,63841614,8555597,67098132,62368609,39205700,42258905,61649350,1224802,41288139,67150573,60252995,66801275,2251556,66907545,67004473,67088624,67103794,42700304,67193496,40810297,67210279,,64942487,1134755,60347315,67236214,66144535,63849256", "17": ",867926538,854270809,869804045,857316962"}, "this_visit_rows": 3375}, "__F": {"custom_level": "[{r:-21000,n:\"内鬼\"},{r:-500,n:\"st退\"},{r:-1,n:\"A股新秀\"},{r:150,n:\"每日打新\"},{r:300,n:\"扒车高手\"},{r:500,n:\"做t能手\"},{r:1000,n:\"两融侠客\"},{r:2000,n:\"技术达人\"},{r:3500,n:\"大时代证监会\"},{r:5000,n:\"基金经理\"},{r:10000,n:\"投行专家\"},{r:15000,n:\"股市大亨\"},{r:20000,n:\"万神殿\"}]", "name": "大时代"}, "__R__ROWS": 20, "__R__ROWS_PAGE": 20, "__ROWS": 3375, "__PAGE": 9}, "time": 1782109189}